MultiProcessDivision/__init__.py
MultiProcessDivision/divide.py
MultiProcessDivision-1.0.dist-info/METADATA
MultiProcessDivision-1.0.dist-info/WHEEL
MultiProcessDivision-1.0.dist-info/top_level.txt
MultiProcessDivision-1.0.dist-info/RECORD
