Metadata-Version: 2.1
Name: MultiProcessDivision
Version: 1.0
Summary: This library splits large dataframes into smaller chunks, which are then passed to multiprocessing
Home-page: UNKNOWN
Author: Thomas Rahimi
Author-email: thomas.rahimi@agrar.uni-kassel.de
License: BSD
Platform: UNKNOWN
Classifier: Intended Audience :: Science/Research
Classifier: License :: OSI Approved :: BSD License
Classifier: Operating System :: POSIX :: Linux
Classifier: Programming Language :: Python :: 3
Classifier: Programming Language :: Python :: 3.6
Classifier: Development Status :: 5 - Production/Stable
Requires-Python: >=3.6
Requires-Dist: pandas (>=0.24)
Requires-Dist: numpy (>=1.14)
